moleditpy_linux/__init__.py
moleditpy_linux/__main__.py
moleditpy_linux/assets/icon.ico
moleditpy_linux/assets/icon.png
moleditpy_linux-1.12.4.dist-info/METADATA
moleditpy_linux-1.12.4.dist-info/WHEEL
moleditpy_linux-1.12.4.dist-info/entry_points.txt
moleditpy_linux-1.12.4.dist-info/top_level.txt
moleditpy_linux-1.12.4.dist-info/RECORD
