Metadata-Version: 2.4
Name: moleditpy-linux
Version: 1.12.4
Summary: A cross-platform, simple, and intuitive molecular structure editor buiSlt in Python. It allows 2D molecular drawing and 3D structure visualization. It supports exporting structure files for input to DFT calculation software.
Author-email: HiroYokoyama <titech.yoko.hiro@gmail.com>
Project-URL: Homepage, https://github.com/HiroYokoyama/python_molecular_editor
Project-URL: Issues, https://github.com/HiroYokoyama/python_molecular_editor/issues
Classifier: Programming Language :: Python :: 3
Classifier: Operating System :: OS Independent
Classifier: Intended Audience :: Science/Research
Classifier: Topic :: Scientific/Engineering :: Chemistry
Classifier: Programming Language :: Python :: 3.8
Classifier: Programming Language :: Python :: 3.9
Classifier: Programming Language :: Python :: 3.10
Classifier: Programming Language :: Python :: 3.11
Classifier: Programming Language :: Python :: 3.12
Classifier: Programming Language :: Python :: 3.13
Classifier: License :: OSI Approved :: Apache Software License
Requires-Python: >=3.8
Requires-Dist: numpy
Requires-Dist: pyqt6<6.10
Requires-Dist: pyvista<0.47
Requires-Dist: pyvistaqt<0.12
Requires-Dist: rdkit<2025.10
